simplesocket/__init__.py
simplesocket/simplesocket.py
simplesocket_py-0.1.0.dist-info/METADATA
simplesocket_py-0.1.0.dist-info/WHEEL
simplesocket_py-0.1.0.dist-info/top_level.txt
simplesocket_py-0.1.0.dist-info/RECORD
